LICENSE
patternfly/__init__.py
patternfly/models.py
patternfly/patternfly.py
patternfly/templates/patternfly/patternfly.html
patternfly/templatetags/__init__.py
patternfly/templatetags/patternfly.py
patternfly/text.py
patternfly/utils.py
django_patternfly4-0.0.3.dist-info/LICENSE
django_patternfly4-0.0.3.dist-info/WHEEL
django_patternfly4-0.0.3.dist-info/METADATA
django_patternfly4-0.0.3.dist-info/RECORD
